stactools/noaa_cdr/__init__.py
stactools/noaa_cdr/cog.py
stactools/noaa_cdr/commands.py
stactools/noaa_cdr/constants.py
stactools/noaa_cdr/dataset.py
stactools/noaa_cdr/profile.py
stactools/noaa_cdr/stac.py
stactools/noaa_cdr/time.py
stactools/noaa_cdr/ocean_heat_content/__init__.py
stactools/noaa_cdr/ocean_heat_content/asset-metadata.json
stactools/noaa_cdr/ocean_heat_content/cog.py
stactools/noaa_cdr/ocean_heat_content/commands.py
stactools/noaa_cdr/ocean_heat_content/constants.py
stactools/noaa_cdr/ocean_heat_content/stac.py
stactools/noaa_cdr/sea_ice_concentration/__init__.py
stactools/noaa_cdr/sea_ice_concentration/cog.py
stactools/noaa_cdr/sea_ice_concentration/commands.py
stactools/noaa_cdr/sea_ice_concentration/constants.py
stactools/noaa_cdr/sea_ice_concentration/item-assets.json
stactools/noaa_cdr/sea_ice_concentration/stac.py
stactools/noaa_cdr/sea_surface_temperature_optimum_interpolation/__init__.py
stactools/noaa_cdr/sea_surface_temperature_optimum_interpolation/commands.py
stactools/noaa_cdr/sea_surface_temperature_optimum_interpolation/constants.py
stactools/noaa_cdr/sea_surface_temperature_optimum_interpolation/item-assets.json
stactools/noaa_cdr/sea_surface_temperature_optimum_interpolation/stac.py
stactools/noaa_cdr/sea_surface_temperature_whoi/__init__.py
stactools/noaa_cdr/sea_surface_temperature_whoi/commands.py
stactools/noaa_cdr/sea_surface_temperature_whoi/constants.py
stactools/noaa_cdr/sea_surface_temperature_whoi/item-assets.json
stactools/noaa_cdr/sea_surface_temperature_whoi/stac.py
stactools_noaa_cdr-0.2.1.dist-info/LICENSE
stactools_noaa_cdr-0.2.1.dist-info/METADATA
stactools_noaa_cdr-0.2.1.dist-info/WHEEL
stactools_noaa_cdr-0.2.1.dist-info/top_level.txt
stactools_noaa_cdr-0.2.1.dist-info/RECORD
