Metadata-Version: 2.1
Name: stactools-noaa-cdr
Version: 0.2.1
Summary: NOAA Climate Data Records (CDR) stactools package
Home-page: https://github.com/stactools-packages/noaa-cdr
Author: Pete Gadomski
Author-email: pete.gadomski@gmail.com
Project-URL: Issues, https://github.com/stactools-packages/noaa-cdr/issues
Keywords: stactools,pystac,catalog,STAC,NOAA
Classifier: Development Status :: 4 - Beta
Classifier: License :: OSI Approved :: Apache Software License
Classifier: Programming Language :: Python :: 3.8
Classifier: Programming Language :: Python :: 3.9
Classifier: Programming Language :: Python :: 3.10
License-File: LICENSE
Requires-Dist: click (>=8.1.3)
Requires-Dist: click-logging (>=1.0.1)
Requires-Dist: cftime (>=1.6.2)
Requires-Dist: h5netcdf (>=1.0.2)
Requires-Dist: importlib-resources (>=5.12.0)
Requires-Dist: numpy (>=1.23.1)
Requires-Dist: orjson (>=3.8.0)
Requires-Dist: rasterio (>=1.3.0)
Requires-Dist: requests (>=2.0.0)
Requires-Dist: stactools (>=0.4.0)
Requires-Dist: python-dateutil (>=2.8.2)
Requires-Dist: tqdm (>=4.0.0)
Requires-Dist: xarray (>=2022.6)
